LatexTool/__init__.py
LatexTool/tex_tools.py
LatexTool/totable.py
LatexTool/ast/__init__.py
LatexTool/ast/tabel.py
x2t-0.0.5.dev1.dist-info/METADATA
x2t-0.0.5.dev1.dist-info/WHEEL
x2t-0.0.5.dev1.dist-info/entry_points.txt
x2t-0.0.5.dev1.dist-info/top_level.txt
x2t-0.0.5.dev1.dist-info/RECORD
